{"data":[{"colorscale":[[0.0,"rgb(103,0,31)"],[0.1,"rgb(178,24,43)"],[0.2,"rgb(214,96,77)"],[0.3,"rgb(244,165,130)"],[0.4,"rgb(253,219,199)"],[0.5,"rgb(247,247,247)"],[0.6,"rgb(209,229,240)"],[0.7,"rgb(146,197,222)"],[0.8,"rgb(67,147,195)"],[0.9,"rgb(33,102,172)"],[1.0,"rgb(5,48,97)"]],"text":{"dtype":"f8","bdata":"AAAAAAAA8D9S6WoOEtTvP2F0pZoWEbg\u002fPTghNHkGsj97uwiUp+i1P2NumlX3Goe\u002fpQuUfS66ej8JcY9zWz3vP28\u002fbuLobrE\u002fAfyi\u002fSJHkT9vBmdpk8yRv9Iy\u002fueSoa4\u002fUulqDhLU7z8AAAAAAADwPwdJ839P2Lc\u002f9nCn5Xxgsz+8fuZqQj60P0t4ZVlZuoa\u002fCMaVZBlUhD9WGrYL0k7vP8veVbZ7RLE\u002fA5TWUY0PkT+cbTd5a+eTv7R+5T3Y\u002f6w\u002fYXSlmhYRuD8HSfN\u002fT9i3PwAAAAAAAPA\u002fuajOc23J2z\u002ful+0zTt\u002fTP\u002fZZRgTZO8W\u002fbTMzBlei2D+dABvFeqjAP4hBREQhNc4\u002fqZQzkMCRyT\u002fRfpinGRbRv\u002fNDn4f\u002f8+Q\u002fPTghNHkGsj\u002f2cKflfGCzP7moznNtyds\u002fAAAAAAAA8D9Gcm3W1vjFP7AbWubDDcg\u002fVOKd5\u002fAHw7+DJsT92Iy1P+LBHjbHe9c\u002foSUl1Ggq5D\u002fLGvZAaC3kv2njmvtYe9g\u002fe7sIlKfotT+8fuZqQj60P+6X7TNO39M\u002fRnJt1tb4xT8AAAAAAADwP4M6DdyCzsg\u002fsyVmBBqDq79ebs+Z5GO\u002fPwaA8K+r6+o\u002fI+OFVW8VrT+jzw4dI3uvv6GHM1V2wtU\u002fY26aVfcah79LeGVZWbqGv\u002fZZRgTZO8W\u002fsBta5sMNyD+DOg3cgs7IPwAAAAAAAPA\u002fKuqeTEYiwL\u002fjuuP3TFljv\u002fxDWk35wLw\u002fPicq7d1j2T8pBydcYe7DP1cWMhDw\u002f7o\u002fpQuUfS66ej8IxpVkGVSEP20zMwZXotg\u002fVOKd5\u002fAHw7+zJWYEGoOrvyrqnkxGIsC\u002fAAAAAAAA8D\u002fdgc1p759uP5IWYAlSZ8C\u002fLToqCtuiuL\u002f657aGA4\u002fLP51\u002fN17kvtA\u002fCXGPc1s97z9WGrYL0k7vP50AG8V6qMA\u002fgybE\u002fdiMtT9ebs+Z5GO\u002fP+O64\u002fdMWWO\u002f3YHNae+fbj8AAAAAAADwPx0DVSHNxbg\u002fFfYgg\u002fm3nz+5usnXrzyVv7lj1y283bc\u002fbz9u4uhusT\u002fL3lW2e0SxP4hBREQhNc4\u002f4sEeNsd71z8GgPCvq+vqP\u002fxDWk35wLw\u002fkhZgCVJnwL8dA1UhzcW4PwAAAAAAAPA\u002fPNk+0rX7vD\u002fWupdhwerZvwajfvT9\u002fNk\u002fAfyi\u002fSJHkT8DlNZRjQ+RP6mUM5DAkck\u002foSUl1Ggq5D8j44VVbxWtPz4nKu3dY9k\u002fLToqCtuiuL8V9iCD+befPzzZPtK1+7w\u002fAAAAAAAA8D+qG24WG\u002fHPv7bgVFv54cU\u002fbwZnaZPMkb+cbTd5a+eTv9F+mKcZFtG\u002fyxr2QGgt5L+jzw4dI3uvvykHJ1xh7sM\u002f+ue2hgOPyz+5usnXrzyVv9a6l2HB6tm\u002fqhtuFhvxz78AAAAAAADwPyGdyAOe9ty\u002f0jL+55Khrj+0fuU92P+sP\u002fNDn4f\u002f8+Q\u002faeOa+1h72D+hhzNVdsLVP1cWMhDw\u002f7o\u002fnX83XuS+0D+5Y9ctvN23PwajfvT9\u002fNk\u002ftuBUW\u002fnhxT8hncgDnvbcvwAAAAAAAPA\u002f","shape":"12, 12"},"texttemplate":"%{text:.2f}","x":["Biochemical Oxygen Demand","Chemical Oxygen Demand","Chloride","Conductivity","Depth","Dissolved Oxygen","Nitrate","Total Organic Carbon","Water Level","Water Temperature","Water Turbidity","pH"],"y":["Biochemical Oxygen Demand","Chemical Oxygen Demand","Chloride","Conductivity","Depth","Dissolved Oxygen","Nitrate","Total Organic Carbon","Water Level","Water Temperature","Water Turbidity","pH"],"z":{"dtype":"f8","bdata":"AAAAAAAA8D9S6WoOEtTvP2F0pZoWEbg\u002fPTghNHkGsj97uwiUp+i1P2NumlX3Goe\u002fpQuUfS66ej8JcY9zWz3vP28\u002fbuLobrE\u002fAfyi\u002fSJHkT9vBmdpk8yRv9Iy\u002fueSoa4\u002fUulqDhLU7z8AAAAAAADwPwdJ839P2Lc\u002f9nCn5Xxgsz+8fuZqQj60P0t4ZVlZuoa\u002fCMaVZBlUhD9WGrYL0k7vP8veVbZ7RLE\u002fA5TWUY0PkT+cbTd5a+eTv7R+5T3Y\u002f6w\u002fYXSlmhYRuD8HSfN\u002fT9i3PwAAAAAAAPA\u002fuajOc23J2z\u002ful+0zTt\u002fTP\u002fZZRgTZO8W\u002fbTMzBlei2D+dABvFeqjAP4hBREQhNc4\u002fqZQzkMCRyT\u002fRfpinGRbRv\u002fNDn4f\u002f8+Q\u002fPTghNHkGsj\u002f2cKflfGCzP7moznNtyds\u002fAAAAAAAA8D9Gcm3W1vjFP7AbWubDDcg\u002fVOKd5\u002fAHw7+DJsT92Iy1P+LBHjbHe9c\u002foSUl1Ggq5D\u002fLGvZAaC3kv2njmvtYe9g\u002fe7sIlKfotT+8fuZqQj60P+6X7TNO39M\u002fRnJt1tb4xT8AAAAAAADwP4M6DdyCzsg\u002fsyVmBBqDq79ebs+Z5GO\u002fPwaA8K+r6+o\u002fI+OFVW8VrT+jzw4dI3uvv6GHM1V2wtU\u002fY26aVfcah79LeGVZWbqGv\u002fZZRgTZO8W\u002fsBta5sMNyD+DOg3cgs7IPwAAAAAAAPA\u002fKuqeTEYiwL\u002fjuuP3TFljv\u002fxDWk35wLw\u002fPicq7d1j2T8pBydcYe7DP1cWMhDw\u002f7o\u002fpQuUfS66ej8IxpVkGVSEP20zMwZXotg\u002fVOKd5\u002fAHw7+zJWYEGoOrvyrqnkxGIsC\u002fAAAAAAAA8D\u002fdgc1p759uP5IWYAlSZ8C\u002fLToqCtuiuL\u002f657aGA4\u002fLP51\u002fN17kvtA\u002fCXGPc1s97z9WGrYL0k7vP50AG8V6qMA\u002fgybE\u002fdiMtT9ebs+Z5GO\u002fP+O64\u002fdMWWO\u002f3YHNae+fbj8AAAAAAADwPx0DVSHNxbg\u002fFfYgg\u002fm3nz+5usnXrzyVv7lj1y283bc\u002fbz9u4uhusT\u002fL3lW2e0SxP4hBREQhNc4\u002f4sEeNsd71z8GgPCvq+vqP\u002fxDWk35wLw\u002fkhZgCVJnwL8dA1UhzcW4PwAAAAAAAPA\u002fPNk+0rX7vD\u002fWupdhwerZvwajfvT9\u002fNk\u002fAfyi\u002fSJHkT8DlNZRjQ+RP6mUM5DAkck\u002foSUl1Ggq5D8j44VVbxWtPz4nKu3dY9k\u002fLToqCtuiuL8V9iCD+befPzzZPtK1+7w\u002fAAAAAAAA8D+qG24WG\u002fHPv7bgVFv54cU\u002fbwZnaZPMkb+cbTd5a+eTv9F+mKcZFtG\u002fyxr2QGgt5L+jzw4dI3uvvykHJ1xh7sM\u002f+ue2hgOPyz+5usnXrzyVv9a6l2HB6tm\u002fqhtuFhvxz78AAAAAAADwPyGdyAOe9ty\u002f0jL+55Khrj+0fuU92P+sP\u002fNDn4f\u002f8+Q\u002faeOa+1h72D+hhzNVdsLVP1cWMhDw\u002f7o\u002fnX83XuS+0D+5Y9ctvN23PwajfvT9\u002fNk\u002ftuBUW\u002fnhxT8hncgDnvbcvwAAAAAAAPA\u002f","shape":"12, 12"},"zmax":1,"zmin":-1,"type":"heatmap"}],"layout":{"template":{"data":{"histogram2dcontour":[{"type":"histogram2dcontour","colorbar":{"outlinewidth":0,"ticks":""},"colorscale":[[0.0,"#0d0887"],[0.1111111111111111,"#46039f"],[0.2222222222222222,"#7201a8"],[0.3333333333333333,"#9c179e"],[0.4444444444444444,"#bd3786"],[0.5555555555555556,"#d8576b"],[0.6666666666666666,"#ed7953"],[0.7777777777777778,"#fb9f3a"],[0.8888888888888888,"#fdca26"],[1.0,"#f0f921"]]}],"choropleth":[{"type":"choropleth","colorbar":{"outlinewidth":0,"ticks":""}}],"histogram2d":[{"type":"histogram2d","colorbar":{"outlinewidth":0,"ticks":""},"colorscale":[[0.0,"#0d0887"],[0.1111111111111111,"#46039f"],[0.2222222222222222,"#7201a8"],[0.3333333333333333,"#9c179e"],[0.4444444444444444,"#bd3786"],[0.5555555555555556,"#d8576b"],[0.6666666666666666,"#ed7953"],[0.7777777777777778,"#fb9f3a"],[0.8888888888888888,"#fdca26"],[1.0,"#f0f921"]]}],"heatmap":[{"type":"heatmap","colorbar":{"outlinewidth":0,"ticks":""},"colorscale":[[0.0,"#0d0887"],[0.1111111111111111,"#46039f"],[0.2222222222222222,"#7201a8"],[0.3333333333333333,"#9c179e"],[0.4444444444444444,"#bd3786"],[0.5555555555555556,"#d8576b"],[0.6666666666666666,"#ed7953"],[0.7777777777777778,"#fb9f3a"],[0.8888888888888888,"#fdca26"],[1.0,"#f0f921"]]}],"contourcarpet":[{"type":"contourcarpet","colorbar":{"outlinewidth":0,"ticks":""}}],"contour":[{"type":"contour","colorbar":{"outlinewidth":0,"ticks":""},"colorscale":[[0.0,"#0d0887"],[0.1111111111111111,"#46039f"],[0.2222222222222222,"#7201a8"],[0.3333333333333333,"#9c179e"],[0.4444444444444444,"#bd3786"],[0.5555555555555556,"#d8576b"],[0.6666666666666666,"#ed7953"],[0.7777777777777778,"#fb9f3a"],[0.8888888888888888,"#fdca26"],[1.0,"#f0f921"]]}],"surface":[{"type":"surface","colorbar":{"outlinewidth":0,"ticks":""},"colorscale":[[0.0,"#0d0887"],[0.1111111111111111,"#46039f"],[0.2222222222222222,"#7201a8"],[0.3333333333333333,"#9c179e"],[0.4444444444444444,"#bd3786"],[0.5555555555555556,"#d8576b"],[0.6666666666666666,"#ed7953"],[0.7777777777777778,"#fb9f3a"],[0.8888888888888888,"#fdca26"],[1.0,"#f0f921"]]}],"mesh3d":[{"type":"mesh3d","colorbar":{"outlinewidth":0,"ticks":""}}],"scatter":[{"fillpattern":{"fillmode":"overlay","size":10,"solidity":0.2},"type":"scatter"}],"parcoords":[{"type":"parcoords","line":{"colorbar":{"outlinewidth":0,"ticks":""}}}],"scatterpolargl":[{"type":"scatterpolargl","marker":{"colorbar":{"outlinewidth":0,"ticks":""}}}],"bar":[{"error_x":{"color":"#2a3f5f"},"error_y":{"color":"#2a3f5f"},"marker":{"line":{"color":"#E5ECF6","width":0.5},"pattern":{"fillmode":"overlay","size":10,"solidity":0.2}},"type":"bar"}],"scattergeo":[{"type":"scattergeo","marker":{"colorbar":{"outlinewidth":0,"ticks":""}}}],"scatterpolar":[{"type":"scatterpolar","marker":{"colorbar":{"outlinewidth":0,"ticks":""}}}],"histogram":[{"marker":{"pattern":{"fillmode":"overlay","size":10,"solidity":0.2}},"type":"histogram"}],"scattergl":[{"type":"scattergl","marker":{"colorbar":{"outlinewidth":0,"ticks":""}}}],"scatter3d":[{"type":"scatter3d","line":{"colorbar":{"outlinewidth":0,"ticks":""}},"marker":{"colorbar":{"outlinewidth":0,"ticks":""}}}],"scattermap":[{"type":"scattermap","marker":{"colorbar":{"outlinewidth":0,"ticks":""}}}],"scattermapbox":[{"type":"scattermapbox","marker":{"colorbar":{"outlinewidth":0,"ticks":""}}}],"scatterternary":[{"type":"scatterternary","marker":{"colorbar":{"outlinewidth":0,"ticks":""}}}],"scattercarpet":[{"type":"scattercarpet","marker":{"colorbar":{"outlinewidth":0,"ticks":""}}}],"carpet":[{"aaxis":{"endlinecolor":"#2a3f5f","gridcolor":"white","linecolor":"white","minorgridcolor":"white","startlinecolor":"#2a3f5f"},"baxis":{"endlinecolor":"#2a3f5f","gridcolor":"white","linecolor":"white","minorgridcolor":"white","startlinecolor":"#2a3f5f"},"type":"carpet"}],"table":[{"cells":{"fill":{"color":"#EBF0F8"},"line":{"color":"white"}},"header":{"fill":{"color":"#C8D4E3"},"line":{"color":"white"}},"type":"table"}],"barpolar":[{"marker":{"line":{"color":"#E5ECF6","width":0.5},"pattern":{"fillmode":"overlay","size":10,"solidity":0.2}},"type":"barpolar"}],"pie":[{"automargin":true,"type":"pie"}]},"layout":{"autotypenumbers":"strict","colorway":["#636efa","#EF553B","#00cc96","#ab63fa","#FFA15A","#19d3f3","#FF6692","#B6E880","#FF97FF","#FECB52"],"font":{"color":"#2a3f5f"},"hovermode":"closest","hoverlabel":{"align":"left"},"paper_bgcolor":"white","plot_bgcolor":"#E5ECF6","polar":{"bgcolor":"#E5ECF6","angularaxis":{"gridcolor":"white","linecolor":"white","ticks":""},"radialaxis":{"gridcolor":"white","linecolor":"white","ticks":""}},"ternary":{"bgcolor":"#E5ECF6","aaxis":{"gridcolor":"white","linecolor":"white","ticks":""},"baxis":{"gridcolor":"white","linecolor":"white","ticks":""},"caxis":{"gridcolor":"white","linecolor":"white","ticks":""}},"coloraxis":{"colorbar":{"outlinewidth":0,"ticks":""}},"colorscale":{"sequential":[[0.0,"#0d0887"],[0.1111111111111111,"#46039f"],[0.2222222222222222,"#7201a8"],[0.3333333333333333,"#9c179e"],[0.4444444444444444,"#bd3786"],[0.5555555555555556,"#d8576b"],[0.6666666666666666,"#ed7953"],[0.7777777777777778,"#fb9f3a"],[0.8888888888888888,"#fdca26"],[1.0,"#f0f921"]],"sequentialminus":[[0.0,"#0d0887"],[0.1111111111111111,"#46039f"],[0.2222222222222222,"#7201a8"],[0.3333333333333333,"#9c179e"],[0.4444444444444444,"#bd3786"],[0.5555555555555556,"#d8576b"],[0.6666666666666666,"#ed7953"],[0.7777777777777778,"#fb9f3a"],[0.8888888888888888,"#fdca26"],[1.0,"#f0f921"]],"diverging":[[0,"#8e0152"],[0.1,"#c51b7d"],[0.2,"#de77ae"],[0.3,"#f1b6da"],[0.4,"#fde0ef"],[0.5,"#f7f7f7"],[0.6,"#e6f5d0"],[0.7,"#b8e186"],[0.8,"#7fbc41"],[0.9,"#4d9221"],[1,"#276419"]]},"xaxis":{"gridcolor":"white","linecolor":"white","ticks":"","title":{"standoff":15},"zerolinecolor":"white","automargin":true,"zerolinewidth":2},"yaxis":{"gridcolor":"white","linecolor":"white","ticks":"","title":{"standoff":15},"zerolinecolor":"white","automargin":true,"zerolinewidth":2},"scene":{"xaxis":{"backgroundcolor":"#E5ECF6","gridcolor":"white","linecolor":"white","showbackground":true,"ticks":"","zerolinecolor":"white","gridwidth":2},"yaxis":{"backgroundcolor":"#E5ECF6","gridcolor":"white","linecolor":"white","showbackground":true,"ticks":"","zerolinecolor":"white","gridwidth":2},"zaxis":{"backgroundcolor":"#E5ECF6","gridcolor":"white","linecolor":"white","showbackground":true,"ticks":"","zerolinecolor":"white","gridwidth":2}},"shapedefaults":{"line":{"color":"#2a3f5f"}},"annotationdefaults":{"arrowcolor":"#2a3f5f","arrowhead":0,"arrowwidth":1},"geo":{"bgcolor":"white","landcolor":"#E5ECF6","subunitcolor":"white","showland":true,"showlakes":true,"lakecolor":"white"},"title":{"x":0.05},"mapbox":{"style":"light"}}},"xaxis":{"tickangle":-45},"title":{"text":"Correlation Matrix (Pearson) - Station 11783"},"height":700,"width":800,"meta":{"top_correlated_pairs":{"positive":[{"param1":"Biochemical Oxygen Demand","param2":"Chemical Oxygen Demand","correlation":0.9946375161737626,"abs_corr":0.9946375161737626},{"param1":"Chemical Oxygen Demand","param2":"Total Organic Carbon","correlation":0.9783716419922921,"abs_corr":0.9783716419922921},{"param1":"Biochemical Oxygen Demand","param2":"Total Organic Carbon","correlation":0.9762398964917632,"abs_corr":0.9762398964917632},{"param1":"Depth","param2":"Water Level","correlation":0.8412683903043223,"abs_corr":0.8412683903043223},{"param1":"Chloride","param2":"pH","correlation":0.6547849320287454,"abs_corr":0.6547849320287454}],"negative":[{"param1":"Conductivity","param2":"Water Turbidity","correlation":-0.6305428761268898,"abs_corr":0.6305428761268898},{"param1":"Water Turbidity","param2":"pH","correlation":-0.45255232209679447,"abs_corr":0.45255232209679447},{"param1":"Water Level","param2":"Water Turbidity","correlation":-0.40495333223854624,"abs_corr":0.40495333223854624},{"param1":"Chloride","param2":"Water Turbidity","correlation":-0.26697388998762245,"abs_corr":0.26697388998762245},{"param1":"Water Temperature","param2":"Water Turbidity","correlation":-0.2495454654237766,"abs_corr":0.2495454654237766}]}}}}