{"data":[{"colorscale":[[0.0,"rgb(103,0,31)"],[0.1,"rgb(178,24,43)"],[0.2,"rgb(214,96,77)"],[0.3,"rgb(244,165,130)"],[0.4,"rgb(253,219,199)"],[0.5,"rgb(247,247,247)"],[0.6,"rgb(209,229,240)"],[0.7,"rgb(146,197,222)"],[0.8,"rgb(67,147,195)"],[0.9,"rgb(33,102,172)"],[1.0,"rgb(5,48,97)"]],"text":{"dtype":"f8","bdata":"AAAAAAAA8D9paZj95dnvPyFVIirXZp+\u002fOfucD2PLxj\u002f3+s1avRHTP33ChmrKzeQ\u002fY5keK8MW1D8Wv0V1gW7vP+VEMPLKYtA\u002fTS0LmiDMzb9UTMOgKbbSP7Lgj2bpz98\u002faWmY\u002feXZ7z8AAAAAAADwP19Hx27X9qe\u002fQcBs\u002fYM4xT9dOVsky6LSP4A2dqhYxeQ\u002fI0pf0hAp1T9Sf7SAzkbvPw8DRebtvM8\u002f9ofGYc0Jzb\u002ffnWSIb7LSP4\u002f08IUY+98\u002fIVUiKtdmn79fR8du1\u002fanvwAAAAAAAPA\u002fRUjA5M3+6D8UlD1f3RrkP64DS\u002fLt2FK\u002fqHDg5bJA4b9mnyFlpwKWvzgjJtnU9OE\u002fMOwYfm3skT9O5KSW3zLivyz\u002fUGl88rS\u002fOfucD2PLxj9BwGz9gzjFP0VIwOTN\u002fug\u002fAAAAAAAA8D8B32Aeo8jsP9gi1PkbPMs\u002fyp3LNEDK0b+fVrkNpYPGP+sXleo2V+s\u002f8yuMoVGAiL\u002fPq\u002fA9jUfTv1RGotO+9sg\u002f9\u002frNWr0R0z9dOVsky6LSPxSUPV\u002fdGuQ\u002fAd9gHqPI7D8AAAAAAADwP\u002fL1vAqY99Q\u002f\u002fjC6A8uAxb\u002fADE+tpkrTP35W8ip8x+4\u002fXnukbL5\u002fxL\u002fLxbmijgvHv+C2LJiAkNQ\u002ffcKGasrN5D+ANnaoWMXkP64DS\u002fLt2FK\u002f2CLU+Rs8yz\u002fy9bwKmPfUPwAAAAAAAPA\u002fheNTspvlvT+JjJyCuYLkP6zy2wZAR9Y\u002fiWQf3IaO278wgFj2IB\u002fZP12E7mh0LtI\u002fY5keK8MW1D8jSl\u002fSECnVP6hw4OWyQOG\u002fyp3LNEDK0b\u002f+MLoDy4DFv4XjU7Kb5b0\u002fAAAAAAAA8D9hmLoVtw3UP+bUfeTeF86\u002fAr6FIqWtxT\u002fk2oKwcWHJP6dArVtSh+I\u002fFr9FdYFu7z9Sf7SAzkbvP2afIWWnApa\u002fn1a5DaWDxj\u002fADE+tpkrTP4mMnIK5guQ\u002fYZi6FbcN1D8AAAAAAADwP595UXRs588\u002f76iV9qDkzb\u002fmhUJranfQP9utIDHmxt8\u002f5UQw8spi0D8PA0Xm7bzPPzgjJtnU9OE\u002f6xeV6jZX6z9+VvIqfMfuP6zy2wZAR9Y\u002f5tR95N4Xzr+feVF0bOfPPwAAAAAAAPA\u002feRtQULj20L9rXwwfM1Sdv3o6Qz2mTtM\u002fTS0LmiDMzb\u002f2h8ZhzQnNvzDsGH5t7JE\u002f8yuMoVGAiL9ee6Rsvn\u002fEv4lkH9yGjtu\u002fAr6FIqWtxT\u002fvqJX2oOTNv3kbUFC49tC\u002fAAAAAAAA8D\u002ffPWUSP13Zv9b6ilS83c2\u002fVEzDoCm20j\u002ffnWSIb7LSP07kpJbfMuK\u002fz6vwPY1H07\u002fLxbmijgvHvzCAWPYgH9k\u002f5NqCsHFhyT\u002fmhUJranfQP2tfDB8zVJ2\u002f3z1lEj9d2b8AAAAAAADwPz8IVt93gMM\u002fsuCPZunP3z+P9PCFGPvfPyz\u002fUGl88rS\u002fVEai0772yD\u002fgtiyYgJDUP12E7mh0LtI\u002fp0CtW1KH4j\u002fbrSAx5sbfP3o6Qz2mTtM\u002f1vqKVLzdzb8\u002fCFbfd4DDPwAAAAAAAPA\u002f","shape":"12, 12"},"texttemplate":"%{text:.2f}","x":["Biochemical Oxygen Demand","Chemical Oxygen Demand","Chloride","Conductivity","Depth","Dissolved Oxygen","Nitrate","Total Organic Carbon","Water Level","Water Temperature","Water Turbidity","pH"],"y":["Biochemical Oxygen Demand","Chemical Oxygen Demand","Chloride","Conductivity","Depth","Dissolved Oxygen","Nitrate","Total Organic Carbon","Water Level","Water Temperature","Water Turbidity","pH"],"z":{"dtype":"f8","bdata":"AAAAAAAA8D9paZj95dnvPyFVIirXZp+\u002fOfucD2PLxj\u002f3+s1avRHTP33ChmrKzeQ\u002fY5keK8MW1D8Wv0V1gW7vP+VEMPLKYtA\u002fTS0LmiDMzb9UTMOgKbbSP7Lgj2bpz98\u002faWmY\u002feXZ7z8AAAAAAADwP19Hx27X9qe\u002fQcBs\u002fYM4xT9dOVsky6LSP4A2dqhYxeQ\u002fI0pf0hAp1T9Sf7SAzkbvPw8DRebtvM8\u002f9ofGYc0Jzb\u002ffnWSIb7LSP4\u002f08IUY+98\u002fIVUiKtdmn79fR8du1\u002fanvwAAAAAAAPA\u002fRUjA5M3+6D8UlD1f3RrkP64DS\u002fLt2FK\u002fqHDg5bJA4b9mnyFlpwKWvzgjJtnU9OE\u002fMOwYfm3skT9O5KSW3zLivyz\u002fUGl88rS\u002fOfucD2PLxj9BwGz9gzjFP0VIwOTN\u002fug\u002fAAAAAAAA8D8B32Aeo8jsP9gi1PkbPMs\u002fyp3LNEDK0b+fVrkNpYPGP+sXleo2V+s\u002f8yuMoVGAiL\u002fPq\u002fA9jUfTv1RGotO+9sg\u002f9\u002frNWr0R0z9dOVsky6LSPxSUPV\u002fdGuQ\u002fAd9gHqPI7D8AAAAAAADwP\u002fL1vAqY99Q\u002f\u002fjC6A8uAxb\u002fADE+tpkrTP35W8ip8x+4\u002fXnukbL5\u002fxL\u002fLxbmijgvHv+C2LJiAkNQ\u002ffcKGasrN5D+ANnaoWMXkP64DS\u002fLt2FK\u002f2CLU+Rs8yz\u002fy9bwKmPfUPwAAAAAAAPA\u002fheNTspvlvT+JjJyCuYLkP6zy2wZAR9Y\u002fiWQf3IaO278wgFj2IB\u002fZP12E7mh0LtI\u002fY5keK8MW1D8jSl\u002fSECnVP6hw4OWyQOG\u002fyp3LNEDK0b\u002f+MLoDy4DFv4XjU7Kb5b0\u002fAAAAAAAA8D9hmLoVtw3UP+bUfeTeF86\u002fAr6FIqWtxT\u002fk2oKwcWHJP6dArVtSh+I\u002fFr9FdYFu7z9Sf7SAzkbvP2afIWWnApa\u002fn1a5DaWDxj\u002fADE+tpkrTP4mMnIK5guQ\u002fYZi6FbcN1D8AAAAAAADwP595UXRs588\u002f76iV9qDkzb\u002fmhUJranfQP9utIDHmxt8\u002f5UQw8spi0D8PA0Xm7bzPPzgjJtnU9OE\u002f6xeV6jZX6z9+VvIqfMfuP6zy2wZAR9Y\u002f5tR95N4Xzr+feVF0bOfPPwAAAAAAAPA\u002feRtQULj20L9rXwwfM1Sdv3o6Qz2mTtM\u002fTS0LmiDMzb\u002f2h8ZhzQnNvzDsGH5t7JE\u002f8yuMoVGAiL9ee6Rsvn\u002fEv4lkH9yGjtu\u002fAr6FIqWtxT\u002fvqJX2oOTNv3kbUFC49tC\u002fAAAAAAAA8D\u002ffPWUSP13Zv9b6ilS83c2\u002fVEzDoCm20j\u002ffnWSIb7LSP07kpJbfMuK\u002fz6vwPY1H07\u002fLxbmijgvHvzCAWPYgH9k\u002f5NqCsHFhyT\u002fmhUJranfQP2tfDB8zVJ2\u002f3z1lEj9d2b8AAAAAAADwPz8IVt93gMM\u002fsuCPZunP3z+P9PCFGPvfPyz\u002fUGl88rS\u002fVEai0772yD\u002fgtiyYgJDUP12E7mh0LtI\u002fp0CtW1KH4j\u002fbrSAx5sbfP3o6Qz2mTtM\u002f1vqKVLzdzb8\u002fCFbfd4DDPwAAAAAAAPA\u002f","shape":"12, 12"},"zmax":1,"zmin":-1,"type":"heatmap"}],"layout":{"template":{"data":{"histogram2dcontour":[{"type":"histogram2dcontour","colorbar":{"outlinewidth":0,"ticks":""},"colorscale":[[0.0,"#0d0887"],[0.1111111111111111,"#46039f"],[0.2222222222222222,"#7201a8"],[0.3333333333333333,"#9c179e"],[0.4444444444444444,"#bd3786"],[0.5555555555555556,"#d8576b"],[0.6666666666666666,"#ed7953"],[0.7777777777777778,"#fb9f3a"],[0.8888888888888888,"#fdca26"],[1.0,"#f0f921"]]}],"choropleth":[{"type":"choropleth","colorbar":{"outlinewidth":0,"ticks":""}}],"histogram2d":[{"type":"histogram2d","colorbar":{"outlinewidth":0,"ticks":""},"colorscale":[[0.0,"#0d0887"],[0.1111111111111111,"#46039f"],[0.2222222222222222,"#7201a8"],[0.3333333333333333,"#9c179e"],[0.4444444444444444,"#bd3786"],[0.5555555555555556,"#d8576b"],[0.6666666666666666,"#ed7953"],[0.7777777777777778,"#fb9f3a"],[0.8888888888888888,"#fdca26"],[1.0,"#f0f921"]]}],"heatmap":[{"type":"heatmap","colorbar":{"outlinewidth":0,"ticks":""},"colorscale":[[0.0,"#0d0887"],[0.1111111111111111,"#46039f"],[0.2222222222222222,"#7201a8"],[0.3333333333333333,"#9c179e"],[0.4444444444444444,"#bd3786"],[0.5555555555555556,"#d8576b"],[0.6666666666666666,"#ed7953"],[0.7777777777777778,"#fb9f3a"],[0.8888888888888888,"#fdca26"],[1.0,"#f0f921"]]}],"contourcarpet":[{"type":"contourcarpet","colorbar":{"outlinewidth":0,"ticks":""}}],"contour":[{"type":"contour","colorbar":{"outlinewidth":0,"ticks":""},"colorscale":[[0.0,"#0d0887"],[0.1111111111111111,"#46039f"],[0.2222222222222222,"#7201a8"],[0.3333333333333333,"#9c179e"],[0.4444444444444444,"#bd3786"],[0.5555555555555556,"#d8576b"],[0.6666666666666666,"#ed7953"],[0.7777777777777778,"#fb9f3a"],[0.8888888888888888,"#fdca26"],[1.0,"#f0f921"]]}],"surface":[{"type":"surface","colorbar":{"outlinewidth":0,"ticks":""},"colorscale":[[0.0,"#0d0887"],[0.1111111111111111,"#46039f"],[0.2222222222222222,"#7201a8"],[0.3333333333333333,"#9c179e"],[0.4444444444444444,"#bd3786"],[0.5555555555555556,"#d8576b"],[0.6666666666666666,"#ed7953"],[0.7777777777777778,"#fb9f3a"],[0.8888888888888888,"#fdca26"],[1.0,"#f0f921"]]}],"mesh3d":[{"type":"mesh3d","colorbar":{"outlinewidth":0,"ticks":""}}],"scatter":[{"fillpattern":{"fillmode":"overlay","size":10,"solidity":0.2},"type":"scatter"}],"parcoords":[{"type":"parcoords","line":{"colorbar":{"outlinewidth":0,"ticks":""}}}],"scatterpolargl":[{"type":"scatterpolargl","marker":{"colorbar":{"outlinewidth":0,"ticks":""}}}],"bar":[{"error_x":{"color":"#2a3f5f"},"error_y":{"color":"#2a3f5f"},"marker":{"line":{"color":"#E5ECF6","width":0.5},"pattern":{"fillmode":"overlay","size":10,"solidity":0.2}},"type":"bar"}],"scattergeo":[{"type":"scattergeo","marker":{"colorbar":{"outlinewidth":0,"ticks":""}}}],"scatterpolar":[{"type":"scatterpolar","marker":{"colorbar":{"outlinewidth":0,"ticks":""}}}],"histogram":[{"marker":{"pattern":{"fillmode":"overlay","size":10,"solidity":0.2}},"type":"histogram"}],"scattergl":[{"type":"scattergl","marker":{"colorbar":{"outlinewidth":0,"ticks":""}}}],"scatter3d":[{"type":"scatter3d","line":{"colorbar":{"outlinewidth":0,"ticks":""}},"marker":{"colorbar":{"outlinewidth":0,"ticks":""}}}],"scattermap":[{"type":"scattermap","marker":{"colorbar":{"outlinewidth":0,"ticks":""}}}],"scattermapbox":[{"type":"scattermapbox","marker":{"colorbar":{"outlinewidth":0,"ticks":""}}}],"scatterternary":[{"type":"scatterternary","marker":{"colorbar":{"outlinewidth":0,"ticks":""}}}],"scattercarpet":[{"type":"scattercarpet","marker":{"colorbar":{"outlinewidth":0,"ticks":""}}}],"carpet":[{"aaxis":{"endlinecolor":"#2a3f5f","gridcolor":"white","linecolor":"white","minorgridcolor":"white","startlinecolor":"#2a3f5f"},"baxis":{"endlinecolor":"#2a3f5f","gridcolor":"white","linecolor":"white","minorgridcolor":"white","startlinecolor":"#2a3f5f"},"type":"carpet"}],"table":[{"cells":{"fill":{"color":"#EBF0F8"},"line":{"color":"white"}},"header":{"fill":{"color":"#C8D4E3"},"line":{"color":"white"}},"type":"table"}],"barpolar":[{"marker":{"line":{"color":"#E5ECF6","width":0.5},"pattern":{"fillmode":"overlay","size":10,"solidity":0.2}},"type":"barpolar"}],"pie":[{"automargin":true,"type":"pie"}]},"layout":{"autotypenumbers":"strict","colorway":["#636efa","#EF553B","#00cc96","#ab63fa","#FFA15A","#19d3f3","#FF6692","#B6E880","#FF97FF","#FECB52"],"font":{"color":"#2a3f5f"},"hovermode":"closest","hoverlabel":{"align":"left"},"paper_bgcolor":"white","plot_bgcolor":"#E5ECF6","polar":{"bgcolor":"#E5ECF6","angularaxis":{"gridcolor":"white","linecolor":"white","ticks":""},"radialaxis":{"gridcolor":"white","linecolor":"white","ticks":""}},"ternary":{"bgcolor":"#E5ECF6","aaxis":{"gridcolor":"white","linecolor":"white","ticks":""},"baxis":{"gridcolor":"white","linecolor":"white","ticks":""},"caxis":{"gridcolor":"white","linecolor":"white","ticks":""}},"coloraxis":{"colorbar":{"outlinewidth":0,"ticks":""}},"colorscale":{"sequential":[[0.0,"#0d0887"],[0.1111111111111111,"#46039f"],[0.2222222222222222,"#7201a8"],[0.3333333333333333,"#9c179e"],[0.4444444444444444,"#bd3786"],[0.5555555555555556,"#d8576b"],[0.6666666666666666,"#ed7953"],[0.7777777777777778,"#fb9f3a"],[0.8888888888888888,"#fdca26"],[1.0,"#f0f921"]],"sequentialminus":[[0.0,"#0d0887"],[0.1111111111111111,"#46039f"],[0.2222222222222222,"#7201a8"],[0.3333333333333333,"#9c179e"],[0.4444444444444444,"#bd3786"],[0.5555555555555556,"#d8576b"],[0.6666666666666666,"#ed7953"],[0.7777777777777778,"#fb9f3a"],[0.8888888888888888,"#fdca26"],[1.0,"#f0f921"]],"diverging":[[0,"#8e0152"],[0.1,"#c51b7d"],[0.2,"#de77ae"],[0.3,"#f1b6da"],[0.4,"#fde0ef"],[0.5,"#f7f7f7"],[0.6,"#e6f5d0"],[0.7,"#b8e186"],[0.8,"#7fbc41"],[0.9,"#4d9221"],[1,"#276419"]]},"xaxis":{"gridcolor":"white","linecolor":"white","ticks":"","title":{"standoff":15},"zerolinecolor":"white","automargin":true,"zerolinewidth":2},"yaxis":{"gridcolor":"white","linecolor":"white","ticks":"","title":{"standoff":15},"zerolinecolor":"white","automargin":true,"zerolinewidth":2},"scene":{"xaxis":{"backgroundcolor":"#E5ECF6","gridcolor":"white","linecolor":"white","showbackground":true,"ticks":"","zerolinecolor":"white","gridwidth":2},"yaxis":{"backgroundcolor":"#E5ECF6","gridcolor":"white","linecolor":"white","showbackground":true,"ticks":"","zerolinecolor":"white","gridwidth":2},"zaxis":{"backgroundcolor":"#E5ECF6","gridcolor":"white","linecolor":"white","showbackground":true,"ticks":"","zerolinecolor":"white","gridwidth":2}},"shapedefaults":{"line":{"color":"#2a3f5f"}},"annotationdefaults":{"arrowcolor":"#2a3f5f","arrowhead":0,"arrowwidth":1},"geo":{"bgcolor":"white","landcolor":"#E5ECF6","subunitcolor":"white","showland":true,"showlakes":true,"lakecolor":"white"},"title":{"x":0.05},"mapbox":{"style":"light"}}},"xaxis":{"tickangle":-45},"title":{"text":"Correlation Matrix (Spearman) - Station 11789"},"height":700,"width":800,"meta":{"top_correlated_pairs":{"positive":[{"param1":"Biochemical Oxygen Demand","param2":"Chemical Oxygen Demand","correlation":0.9953489258798928,"abs_corr":0.9953489258798928},{"param1":"Biochemical Oxygen Demand","param2":"Total Organic Carbon","correlation":0.9822394648053627,"abs_corr":0.9822394648053627},{"param1":"Chemical Oxygen Demand","param2":"Total Organic Carbon","correlation":0.97739339006146,"abs_corr":0.97739339006146},{"param1":"Depth","param2":"Water Level","correlation":0.9618511999894535,"abs_corr":0.9618511999894535},{"param1":"Conductivity","param2":"Depth","correlation":0.8994918435409717,"abs_corr":0.8994918435409717}],"negative":[{"param1":"Chloride","param2":"Water Turbidity","correlation":-0.5687101309077975,"abs_corr":0.5687101309077975},{"param1":"Chloride","param2":"Nitrate","correlation":-0.5391478051929157,"abs_corr":0.5391478051929157},{"param1":"Dissolved Oxygen","param2":"Water Temperature","correlation":-0.43057414528227206,"abs_corr":0.43057414528227206},{"param1":"Water Temperature","param2":"Water Turbidity","correlation":-0.39631630703385484,"abs_corr":0.39631630703385484},{"param1":"Conductivity","param2":"Water Turbidity","correlation":-0.30124217079963683,"abs_corr":0.30124217079963683}]}}}}