{"2025-10-22 (Day 1)":{"Biochemical Oxygen Demand":1.145,"Chemical Oxygen Demand":19.878,"Chloride":40.019,"Conductivity":317.406,"Depth":0.804,"Dissolved Oxygen":5.574,"Nitrate":10.473,"Total Organic Carbon":7.069,"Water Level":206.843,"Water Temperature":28.474,"Water Turbidity":-149.669,"pH":7.465},"2025-10-23 (Day 2)":{"Biochemical Oxygen Demand":1.711,"Chemical Oxygen Demand":18.61,"Chloride":38.785,"Conductivity":330.215,"Depth":0.781,"Dissolved Oxygen":5.303,"Nitrate":10.564,"Total Organic Carbon":7.267,"Water Level":206.837,"Water Temperature":28.45,"Water Turbidity":-131.408,"pH":7.45},"2025-10-24 (Day 3)":{"Biochemical Oxygen Demand":2.236,"Chemical Oxygen Demand":17.58,"Chloride":37.274,"Conductivity":337.913,"Depth":0.77,"Dissolved Oxygen":5.1,"Nitrate":10.596,"Total Organic Carbon":7.547,"Water Level":206.836,"Water Temperature":28.466,"Water Turbidity":-127.872,"pH":7.409},"2025-10-25 (Day 4)":{"Biochemical Oxygen Demand":2.652,"Chemical Oxygen Demand":17.084,"Chloride":35.991,"Conductivity":346.267,"Depth":0.76,"Dissolved Oxygen":4.931,"Nitrate":10.586,"Total Organic Carbon":7.767,"Water Level":206.834,"Water Temperature":28.483,"Water Turbidity":-125.915,"pH":7.369},"2025-10-26 (Day 5)":{"Biochemical Oxygen Demand":3.028,"Chemical Oxygen Demand":17.007,"Chloride":35.147,"Conductivity":355.992,"Depth":0.751,"Dissolved Oxygen":4.779,"Nitrate":10.547,"Total Organic Carbon":7.996,"Water Level":206.831,"Water Temperature":28.499,"Water Turbidity":-124.056,"pH":7.334},"2025-10-27 (Day 6)":{"Biochemical Oxygen Demand":3.403,"Chemical Oxygen Demand":17.515,"Chloride":34.657,"Conductivity":366.988,"Depth":0.742,"Dissolved Oxygen":4.618,"Nitrate":10.492,"Total Organic Carbon":8.224,"Water Level":206.825,"Water Temperature":28.492,"Water Turbidity":-120.373,"pH":7.286},"2025-10-28 (Day 7)":{"Biochemical Oxygen Demand":3.739,"Chemical Oxygen Demand":18.266,"Chloride":34.439,"Conductivity":378.059,"Depth":0.734,"Dissolved Oxygen":4.461,"Nitrate":10.443,"Total Organic Carbon":8.441,"Water Level":206.818,"Water Temperature":28.46,"Water Turbidity":-115.529,"pH":7.234},"Avg":{"Biochemical Oxygen Demand":2.559,"Chemical Oxygen Demand":17.991,"Chloride":36.616,"Conductivity":347.549,"Depth":0.763,"Dissolved Oxygen":4.967,"Nitrate":10.529,"Total Organic Carbon":7.759,"Water Level":206.832,"Water Temperature":28.475,"Water Turbidity":-127.832,"pH":7.364},"Min":{"Biochemical Oxygen Demand":1.145,"Chemical Oxygen Demand":17.007,"Chloride":34.439,"Conductivity":317.406,"Depth":0.734,"Dissolved Oxygen":4.461,"Nitrate":10.443,"Total Organic Carbon":7.069,"Water Level":206.818,"Water Temperature":28.45,"Water Turbidity":-149.669,"pH":7.234},"Max":{"Biochemical Oxygen Demand":3.739,"Chemical Oxygen Demand":19.878,"Chloride":40.019,"Conductivity":378.059,"Depth":0.804,"Dissolved Oxygen":5.574,"Nitrate":10.596,"Total Organic Carbon":8.441,"Water Level":206.843,"Water Temperature":28.499,"Water Turbidity":-115.529,"pH":7.465},"Std":{"Biochemical Oxygen Demand":0.927,"Chemical Oxygen Demand":1.017,"Chloride":2.154,"Conductivity":21.149,"Depth":0.024,"Dissolved Oxygen":0.39,"Nitrate":0.059,"Total Organic Carbon":0.5,"Water Level":0.008,"Water Temperature":0.018,"Water Turbidity":10.913,"pH":0.085}}